uipath_connectors/microsoft_onedrive/__init__.py
uipath_connectors/microsoft_onedrive/client.py
uipath_connectors/microsoft_onedrive/errors.py
uipath_connectors/microsoft_onedrive/py.typed
uipath_connectors/microsoft_onedrive/types.py
uipath_connectors/microsoft_onedrive/api/__init__.py
uipath_connectors/microsoft_onedrive/api/add_sheet/__init__.py
uipath_connectors/microsoft_onedrive/api/add_sheet/add_sheet.py
uipath_connectors/microsoft_onedrive/api/copy_file_folder/__init__.py
uipath_connectors/microsoft_onedrive/api/copy_file_folder/copy_file_folder.py
uipath_connectors/microsoft_onedrive/api/create_folder/__init__.py
uipath_connectors/microsoft_onedrive/api/create_folder/create_folder.py
uipath_connectors/microsoft_onedrive/api/create_share_link/__init__.py
uipath_connectors/microsoft_onedrive/api/create_share_link/create_share_link.py
uipath_connectors/microsoft_onedrive/api/create_workbook/__init__.py
uipath_connectors/microsoft_onedrive/api/create_workbook/create_workbook.py
uipath_connectors/microsoft_onedrive/api/curated_file/__init__.py
uipath_connectors/microsoft_onedrive/api/curated_file/curated_file.py
uipath_connectors/microsoft_onedrive/api/curated_file/get_file_list.py
uipath_connectors/microsoft_onedrive/api/curated_file_and_folder/__init__.py
uipath_connectors/microsoft_onedrive/api/curated_file_and_folder/curated_file_and_folder.py
uipath_connectors/microsoft_onedrive/api/curated_file_and_folder/get_file_folder.py
uipath_connectors/microsoft_onedrive/api/delete_column/__init__.py
uipath_connectors/microsoft_onedrive/api/delete_column/delete_column.py
uipath_connectors/microsoft_onedrive/api/delete_file_folder/__init__.py
uipath_connectors/microsoft_onedrive/api/delete_file_folder/delete_file_folder.py
uipath_connectors/microsoft_onedrive/api/delete_range/__init__.py
uipath_connectors/microsoft_onedrive/api/delete_range/delete_range.py
uipath_connectors/microsoft_onedrive/api/delete_row/__init__.py
uipath_connectors_microsoft_onedrive-1.23.1.dev12.dist-info/METADATA
uipath_connectors_microsoft_onedrive-1.23.1.dev12.dist-info/WHEEL
uipath_connectors_microsoft_onedrive-1.23.1.dev12.dist-info/entry_points.txt
uipath_connectors_microsoft_onedrive-1.23.1.dev12.dist-info/top_level.txt
uipath_connectors_microsoft_onedrive-1.23.1.dev12.dist-info/RECORD
